bbc_feeds/__init__.py
bbc_feeds-2.1.data/scripts/bbc
bbc_feeds-2.1.dist-info/LICENSE
bbc_feeds-2.1.dist-info/METADATA
bbc_feeds-2.1.dist-info/WHEEL
bbc_feeds-2.1.dist-info/top_level.txt
bbc_feeds-2.1.dist-info/RECORD
