Metadata-Version: 2.1
Name: bbc-feeds
Version: 2.1
Summary: A python package to get news, weather, and sports from BBC
Home-page: https://github.com/gadhagod/bbc-feeds
Author: Aarav Borthakur
Author-email: gadhaguy13@gmail.com
License: UNKNOWN
Platform: UNKNOWN
Classifier: Programming Language :: Python :: 3
Classifier: License :: OSI Approved :: MIT License
Classifier: Operating System :: OS Independent
Requires-Python: >=3.6
Requires-Dist: feedparser
Requires-Dist: click
